[
    {
        "title": "HTML",
        "ImgSrc" :"html.png"
    },
    {
        "title": "CSS",
        "ImgSrc" :"css.png"
    },
    {
        "title": "Javascript",
        "ImgSrc" :"javascript.png"
    },    
    {
        "title": "React",
        "ImgSrc" :"react.png"
    },
    {
        "title": "Node",
        "ImgSrc" :"node.png"
    },
    {
        "title": "MongoDB",
        "ImgSrc" :"mongodb.png"
    },
    {
        "title": "Figma",
        "ImgSrc" :"figma.png"
    },
    {
        "title": "Git",
        "ImgSrc" :"git.png"
    },
    {
        "title": "PostgreSQL",
        "ImgSrc" :"postgresql.png"
    }
]